.hgignore
setup.cfg
setup.py
SchevoZodb.egg-info/PKG-INFO
SchevoZodb.egg-info/SOURCES.txt
SchevoZodb.egg-info/dependency_links.txt
SchevoZodb.egg-info/entry_points.txt
SchevoZodb.egg-info/not-zip-safe
SchevoZodb.egg-info/paster_plugins.txt
SchevoZodb.egg-info/requires.txt
SchevoZodb.egg-info/top_level.txt
schevozodb/__init__.py
schevozodb/backend.py
schevozodb/backend_test_classes.py
schevozodb/test/__init__.py
schevozodb/test/test_zodb_backend.py
